odoo/addons/fieldservice_substatus/README.rst
odoo/addons/fieldservice_substatus/__init__.py
odoo/addons/fieldservice_substatus/__manifest__.py
odoo/addons/fieldservice_substatus/data/fsm_stage_status.xml
odoo/addons/fieldservice_substatus/models/__init__.py
odoo/addons/fieldservice_substatus/models/fsm_order.py
odoo/addons/fieldservice_substatus/models/fsm_stage.py
odoo/addons/fieldservice_substatus/models/fsm_stage_status.py
odoo/addons/fieldservice_substatus/readme/CONFIGURE.rst
odoo/addons/fieldservice_substatus/readme/CONTRIBUTORS.rst
odoo/addons/fieldservice_substatus/readme/CREDITS.rst
odoo/addons/fieldservice_substatus/readme/DESCRIPTION.rst
odoo/addons/fieldservice_substatus/readme/INSTALL.rst
odoo/addons/fieldservice_substatus/readme/ROADMAP.rst
odoo/addons/fieldservice_substatus/readme/USAGE.rst
odoo/addons/fieldservice_substatus/security/ir.model.access.csv
odoo/addons/fieldservice_substatus/static/description/icon.png
odoo/addons/fieldservice_substatus/static/description/index.html
odoo/addons/fieldservice_substatus/views/fsm_order.xml
odoo/addons/fieldservice_substatus/views/fsm_stage.xml
odoo/addons/fieldservice_substatus/views/fsm_stage_status.xml
odoo11_addon_fieldservice_substatus-11.0.0.0.1.99.dev5.dist-info/METADATA
odoo11_addon_fieldservice_substatus-11.0.0.0.1.99.dev5.dist-info/WHEEL
odoo11_addon_fieldservice_substatus-11.0.0.0.1.99.dev5.dist-info/top_level.txt
odoo11_addon_fieldservice_substatus-11.0.0.0.1.99.dev5.dist-info/RECORD
